Metadata-Version: 2.1
Name: astrolabe-py
Version: 0.0.20
Summary: Tools for working with Astrolabe data.
Home-page: https://github.com/AstrolabeProject/astrolabe_py
Author: Tom Hicks
Author-email: hickst@email.arizona.edu
License: Apache Software License (http://www.apache.org/licenses/LICENSE-2.0)
Keywords: Astrolabe datastore iRods metadata uploading
Platform: UNKNOWN
Classifier: Development Status :: 1 - Planning
Classifier: Environment :: Console
Classifier: Intended Audience :: Developers
Classifier: Intended Audience :: End Users/Desktop
Classifier: Intended Audience :: Science/Research
Classifier: License :: OSI Approved :: Apache Software License
Classifier: Operating System :: POSIX
Classifier: Programming Language :: Python :: 3
Classifier: Topic :: System :: Archiving
Requires-Python: ~=3.6
